README.md
setup.py
genutilities/__init__.py
genutilities/json_object.py
genutilities.egg-info/PKG-INFO
genutilities.egg-info/SOURCES.txt
genutilities.egg-info/dependency_links.txt
genutilities.egg-info/top_level.txt