Metadata-Version: 2.1
Name: genutilities
Version: 0.0.1
Summary: A lib to code in python easily.
Home-page: http://github.com/LavaPower/genutilities
Author: LavaPower
Author-email: lavapower84@gmail.com
License: UNKNOWN
Platform: UNKNOWN
Classifier: Programming Language :: Python
Classifier: Development Status :: 1 - Planning
Classifier: License :: OSI Approved :: GNU General Public License v3 (GPLv3)
Classifier: Natural Language :: English
Classifier: Operating System :: OS Independent
Classifier: Programming Language :: Python :: 3.7
Classifier: Intended Audience :: Developers
